odoo/addons/stock_available/README.rst
odoo/addons/stock_available/__init__.py
odoo/addons/stock_available/__manifest__.py
odoo/addons/stock_available/i18n/ar.po
odoo/addons/stock_available/i18n/ca.po
odoo/addons/stock_available/i18n/cs_CZ.po
odoo/addons/stock_available/i18n/de.po
odoo/addons/stock_available/i18n/el_GR.po
odoo/addons/stock_available/i18n/es.po
odoo/addons/stock_available/i18n/es_ES.po
odoo/addons/stock_available/i18n/es_MX.po
odoo/addons/stock_available/i18n/eu.po
odoo/addons/stock_available/i18n/fi.po
odoo/addons/stock_available/i18n/fr.po
odoo/addons/stock_available/i18n/fr_CH.po
odoo/addons/stock_available/i18n/fr_FR.po
odoo/addons/stock_available/i18n/gl.po
odoo/addons/stock_available/i18n/hr.po
odoo/addons/stock_available/i18n/hr_HR.po
odoo/addons/stock_available/i18n/it.po
odoo/addons/stock_available/i18n/nl.po
odoo/addons/stock_available/i18n/nl_NL.po
odoo/addons/stock_available/i18n/pt.po
odoo/addons/stock_available/i18n/pt_BR.po
odoo/addons/stock_available/i18n/ro.po
odoo/addons/stock_available/i18n/ru.po
odoo/addons/stock_available/i18n/sl.po
odoo/addons/stock_available/i18n/stock_available.pot
odoo/addons/stock_available/i18n/tr.po
odoo/addons/stock_available/i18n/tr_TR.po
odoo/addons/stock_available/i18n/vi_VN.po
odoo/addons/stock_available/i18n/zh_CN.po
odoo/addons/stock_available/models/__init__.py
odoo/addons/stock_available/models/product_product.py
odoo/addons/stock_available/models/product_template.py
odoo/addons/stock_available/readme/CONFIGURE.md
odoo/addons/stock_available/readme/CONTRIBUTORS.md
odoo/addons/stock_available/readme/DESCRIPTION.md
odoo/addons/stock_available/readme/USAGE.md
odoo/addons/stock_available/static/description/icon.png
odoo/addons/stock_available/static/description/index.html
odoo/addons/stock_available/tests/__init__.py
odoo/addons/stock_available/tests/test_stock_available.py
odoo/addons/stock_available/views/product_product_view.xml
odoo/addons/stock_available/views/product_template_view.xml
odoo_addon_stock_available-18.0.1.0.0.2.dist-info/METADATA
odoo_addon_stock_available-18.0.1.0.0.2.dist-info/WHEEL
odoo_addon_stock_available-18.0.1.0.0.2.dist-info/top_level.txt
odoo_addon_stock_available-18.0.1.0.0.2.dist-info/RECORD
