Metadata-Version: 2.1
Name: odoo-addon-stock_available
Version: 18.0.1.0.0.2
Requires-Python: >=3.10
Requires-Dist: odoo==18.0.*
Summary: Stock available to promise
Home-page: https://github.com/OCA/stock-logistics-availability
License: AGPL-3
Author: =?utf-8?q?Num=C3=A9rigraphe=2C_Sodexis=2C_Odoo_Community_Association_=28OCA=29?=
Author-email: support@odoo-community.org
Classifier: Programming Language :: Python
Classifier: Framework :: Odoo
Classifier: Framework :: Odoo :: 18.0
Classifier: License :: OSI Approved :: GNU Affero General Public License v3
Classifier: Development Status :: 5 - Production/Stable
